pyfilemanager/__init__.py
pyfilemanager-1.1.0.dist-info/LICENSE
pyfilemanager-1.1.0.dist-info/METADATA
pyfilemanager-1.1.0.dist-info/WHEEL
pyfilemanager-1.1.0.dist-info/RECORD
