Metadata-Version: 2.1
Name: pyfilemanager
Version: 1.1.0
Summary: Easy to use file search and file path management in python.
License: MIT
Author: Praneeth Namburi
Author-email: praneeth.namburi@gmail.com
Requires-Python: >=3.7,<4.0
Classifier: License :: OSI Approved :: MIT License
Classifier: Programming Language :: Python :: 3
Classifier: Programming Language :: Python :: 3.7
Classifier: Programming Language :: Python :: 3.8
Classifier: Programming Language :: Python :: 3.9
Classifier: Programming Language :: Python :: 3.10
Classifier: Programming Language :: Python :: 3.11
Classifier: Programming Language :: Python :: 3.12
Project-URL: Bug Tracker, https://github.com/praneethnamburi/pyfilemanager/issues
Project-URL: Documentation, https://pyfilemanager.readthedocs.io
Project-URL: Homepage, https://github.com/praneethnamburi/pyfilemanager
